eval_studio_client/__about__.py
eval_studio_client/__init__.py
eval_studio_client/client.py
eval_studio_client/dashboards.py
eval_studio_client/documents.py
eval_studio_client/evaluators.py
eval_studio_client/insights.py
eval_studio_client/leaderboards.py
eval_studio_client/models.py
eval_studio_client/perturbators.py
eval_studio_client/problems.py
eval_studio_client/test_labs.py
eval_studio_client/tests.py
eval_studio_client/utils.py
eval_studio_client/api/__init__.py
eval_studio_client/api/api_client.py
eval_studio_client/api/api_response.py
eval_studio_client/api/configuration.py
eval_studio_client/api/exceptions.py
eval_studio_client/api/rest.py
eval_studio_client/api/api/__init__.py
eval_studio_client/api/api/adversarial_inputs_service_api.py
eval_studio_client/api/api/dashboard_report_service_api.py
eval_studio_client/api/api/dashboard_service_api.py
eval_studio_client/api/api/dashboard_test_case_annotation_service_api.py
eval_studio_client/api/api/document_service_api.py
eval_studio_client/api/api/evaluation_service_api.py
eval_studio_client/api/api/evaluator_service_api.py
eval_studio_client/api/api/human_calibration_service_api.py
eval_studio_client/api/api/info_service_api.py
eval_studio_client/api/api/leaderboard_report_service_api.py
eval_studio_client/api/api/leaderboard_service_api.py
eval_studio_client/api/api/leaderboard_test_case_annotation_service_api.py
eval_studio_client/api/api/model_service_api.py
eval_studio_client/api/api/operation_progress_service_api.py
eval_studio_client/api/api/operation_service_api.py
eval_studio_client/api/api/perturbation_service_api.py
eval_studio_client/api/api/perturbator_service_api.py
eval_studio_client/api/api/prompt_generation_service_api.py
eval_studio_client/api/api/prompt_library_service_api.py
eval_studio_client/api/api/test_case_relationship_service_api.py
eval_studio_client/api/api/test_case_service_api.py
eval_studio_client/api/api/test_class_service_api.py
eval_studio_client-1.3.0.dist-info/METADATA
eval_studio_client-1.3.0.dist-info/WHEEL
eval_studio_client-1.3.0.dist-info/RECORD
