Metadata-Version: 2.4
Name: eval-studio-client
Version: 1.3.0
Project-URL: Source, https://github.com/h2oai/eval-studio/tree/main/client-py/src/
Project-URL: Issues, https://github.com/h2oai/eval-studio/issues
Author-email: "H2O.ai" <support@h2o.ai>
Classifier: Development Status :: 4 - Beta
Classifier: Programming Language :: Python
Classifier: Programming Language :: Python :: 3.9
Classifier: Programming Language :: Python :: 3.10
Classifier: Programming Language :: Python :: 3.11
Requires-Python: >=3.9
Requires-Dist: h11>=0.16.0
Requires-Dist: h2o-authn<3.0.0,>=2.0.0
Requires-Dist: pydantic>=2
Requires-Dist: python-dateutil>=2.5.3
Requires-Dist: typing-extensions>=4.7.1
Requires-Dist: urllib3~=2.6.3
